click_noexit/__init__.py
click_noexit/noexit.py
click_noexit-0.1.0.dist-info/LICENSE
click_noexit-0.1.0.dist-info/METADATA
click_noexit-0.1.0.dist-info/WHEEL
click_noexit-0.1.0.dist-info/RECORD
