Metadata-Version: 2.1
Name: click-noexit
Version: 0.1.0
Summary: Suppresses the default behavior of Click commands to exit the process.
License: MIT
Author: Adrian Macal
Author-email: adma@amacal.pl
Requires-Python: >=3.8
Classifier: License :: OSI Approved :: MIT License
Classifier: Programming Language :: Python :: 3
Classifier: Programming Language :: Python :: 3.8
Classifier: Programming Language :: Python :: 3.9
Classifier: Programming Language :: Python :: 3.10
Classifier: Programming Language :: Python :: 3.11
Classifier: Programming Language :: Python :: 3.12
Requires-Dist: click (>=8.0.0,<9.0.0)
